odoo10_addon_mrp_procurement_analytic-10.0.1.0.0.99.dev10-nspkg.pth
odoo/addons/mrp_procurement_analytic/README.rst
odoo/addons/mrp_procurement_analytic/__init__.py
odoo/addons/mrp_procurement_analytic/__manifest__.py
odoo/addons/mrp_procurement_analytic/i18n/ca.po
odoo/addons/mrp_procurement_analytic/i18n/es.po
odoo/addons/mrp_procurement_analytic/i18n/mrp_procurement_analytic.pot
odoo/addons/mrp_procurement_analytic/models/__init__.py
odoo/addons/mrp_procurement_analytic/models/mrp_production.py
odoo/addons/mrp_procurement_analytic/models/procurement_order.py
odoo/addons/mrp_procurement_analytic/readme/CONTRIBUTORS.rst
odoo/addons/mrp_procurement_analytic/readme/DESCRIPTION.rst
odoo/addons/mrp_procurement_analytic/readme/HISTORY.rst
odoo/addons/mrp_procurement_analytic/readme/INSTALL.rst
odoo/addons/mrp_procurement_analytic/readme/USAGE.rst
odoo/addons/mrp_procurement_analytic/static/description/icon.png
odoo/addons/mrp_procurement_analytic/static/description/index.html
odoo/addons/mrp_procurement_analytic/tests/__init__.py
odoo/addons/mrp_procurement_analytic/tests/test_mrp_procurement_analytic.py
odoo10_addon_mrp_procurement_analytic-10.0.1.0.0.99.dev10.dist-info/METADATA
odoo10_addon_mrp_procurement_analytic-10.0.1.0.0.99.dev10.dist-info/WHEEL
odoo10_addon_mrp_procurement_analytic-10.0.1.0.0.99.dev10.dist-info/namespace_packages.txt
odoo10_addon_mrp_procurement_analytic-10.0.1.0.0.99.dev10.dist-info/top_level.txt
odoo10_addon_mrp_procurement_analytic-10.0.1.0.0.99.dev10.dist-info/RECORD
